CHANGES.rst
LICENSE
MANIFEST.in
README.rst
setup.cfg
setup.py
genc/__init__.py
genc/regions.py
genc/tests.py
genc.egg-info/PKG-INFO
genc.egg-info/SOURCES.txt
genc.egg-info/dependency_links.txt
genc.egg-info/not-zip-safe
genc.egg-info/top_level.txt