Metadata-Version: 1.1
Name: genc
Version: 0.1
Summary: Geopolitical Entities, Names and Codes (GENC)
Home-page: https://github.com/hannosch/genc
Author: Hanno Schlichting
Author-email: hanno@hannosch.eu
License: Apache 2.0
Keywords: country region codes names
Platform: UNKNOWN
Classifier: License :: OSI Approved :: Apache Software License
Classifier: Programming Language :: Python
Classifier: Programming Language :: Python :: 2
Classifier: Programming Language :: Python :: 2.6
Classifier: Programming Language :: Python :: 2.7
Classifier: Programming Language :: Python :: 3
Classifier: Programming Language :: Python :: 3.4
Classifier: Programming Language :: Python :: Implementation :: CPython
